setres
