Metadata-Version: 1.0
Name: setres
Version: 0.5
Summary: Set the resolution in xorg
Home-page: http://github.com/MartijnBraam/setres
Author: Martijn Braam
Author-email: martijn@brixit.nl
License: MIT
Platform: UNKNOWN
